reddit_decider/__init__.py
reddit_decider/prometheus_metrics.py
reddit_decider/py.typed
reddit_experiments/__init__.py
reddit_experiments/py.typed
reddit_experiments/providers/__init__.py
reddit_experiments/providers/base.py
reddit_experiments/providers/feature_flag.py
reddit_experiments/providers/forced_variant.py
reddit_experiments/providers/r2.py
reddit_experiments/providers/simple_experiment.py
reddit_experiments/targeting/__init__.py
reddit_experiments/targeting/base.py
reddit_experiments/targeting/tree_targeting.py
reddit_experiments/variant_sets/__init__.py
reddit_experiments/variant_sets/base.py
reddit_experiments/variant_sets/multi_variant_set.py
reddit_experiments/variant_sets/range_variant_set.py
reddit_experiments/variant_sets/rollout_variant_set.py
reddit_experiments/variant_sets/single_variant_set.py
reddit_experiments-1.10.0.dist-info/LICENSE
reddit_experiments-1.10.0.dist-info/METADATA
reddit_experiments-1.10.0.dist-info/WHEEL
reddit_experiments-1.10.0.dist-info/top_level.txt
reddit_experiments-1.10.0.dist-info/zip-safe
reddit_experiments-1.10.0.dist-info/RECORD
