Metadata-Version: 2.1
Name: reddit-experiments
Version: 1.10.0
Summary: reddit's python experiments framework
Home-page: https://github.com/reddit/experiments.py
Author: reddit
License: BSD
Project-URL: Documentation, https://reddit-experiments.readthedocs.io/
Platform: UNKNOWN
Classifier: Development Status :: 5 - Production/Stable
Classifier: License :: OSI Approved :: BSD License
Classifier: Programming Language :: Python
Classifier: Programming Language :: Python :: 3.8
Classifier: Programming Language :: Python :: 3.9
Classifier: Topic :: Software Development :: Libraries
Requires-Python: >=3.8
Requires-Dist: baseplate (<3.0,>=2.0.0a1)
Requires-Dist: reddit-edgecontext (<2.0,>=1.0.0a3)
Requires-Dist: reddit-decider (~=1.15.0)
Requires-Dist: typing-extensions (<5.0,>=3.10.0.0)
